{
  "_class": "group",
  "booleanOperation": -1,
  "clippingMaskMode": 0,
  "do_objectID": "99855242-01CF-4813-AB6B-90FC77FACA37",
  "exportOptions": {
    "_class": "exportOptions",
    "do_objectID": "2CF48934-0953-4ECE-86CD-671F7F93D5BF",
    "exportFormats": [
    ],
    "includedLayerIds": [
    ],
    "layerOptions": 0,
    "shouldTrim": false
  },
  "frame": {
    "_class": "rect",
    "constrainProportions": false,
    "do_objectID": "D825D13D-76D6-4E79-AD73-9C15E0813449",
    "height": 139,
    "width": 600,
    "x": 0,
    "y": 0
  },
  "groupLayout": {
    "_class": "MSImmutableFreeformGroupLayout",
    "do_objectID": "6217C4B9-4D4F-4499-A5A1-CE553D99277C"
  },
  "hasClickThrough": false,
  "hasClippingMask": false,
  "isFixedToViewport": false,
  "isFlippedHorizontal": false,
  "isFlippedVertical": false,
  "isLocked": false,
  "isVisible": true,
  "layerListExpandedType": 2,
  "layers": [
    {
      "class": "rectangle",
      "id": "9C7172EB-4CB3-491E-8DEF-1A548F3CA590"
    },
    {
      "class": "text",
      "id": "CA2ABE1E-8939-4794-89FA-0210EF068D4D"
    }
  ],
  "name": "Group 9",
  "nameIsFixed": false,
  "resizingConstraint": 63,
  "resizingType": 0,
  "rotation": 0,
  "shouldBreakMaskChain": false,
  "style": {
    "_class": "style",
    "do_objectID": "5B25A8C5-D7A3-4FEC-BD5D-0FF5FA8DBCC0",
    "endMarkerType": 0,
    "miterLimit": 10,
    "startMarkerType": 0,
    "windingRule": 1
  }
}