{
  "_class": "shapePath",
  "booleanOperation": -1,
  "clippingMaskMode": 0,
  "do_objectID": "5A1D31A2-D7E5-4877-85FE-AE43AAFE287B",
  "edited": true,
  "exportOptions": {
    "_class": "exportOptions",
    "exportFormats": [
    ],
    "includedLayerIds": [
    ],
    "layerOptions": 0,
    "shouldTrim": false
  },
  "frame": {
    "_class": "rect",
    "constrainProportions": false,
    "height": 14.67100000000001,
    "width": 12.369,
    "x": 36.839,
    "y": 20.377
  },
  "hasClippingMask": false,
  "isClosed": true,
  "isFixedToViewport": false,
  "isFlippedHorizontal": false,
  "isFlippedVertical": false,
  "isLocked": false,
  "isVisible": true,
  "layerListExpandedType": 0,
  "name": "Path",
  "nameIsFixed": false,
  "pointRadiusBehaviour": 1,
  "points": [
    {
      "_class": "curvePoint",
      "cornerRadius": 0,
      "curveFrom": "{0.25208181744684366, 0}",
      "curveMode": 1,
      "curveTo": "{0.25208181744684366, 0}",
      "hasCurveFrom": false,
      "hasCurveTo": false,
      "point": "{0.25208181744684366, 0}"
    },
    {
      "_class": "curvePoint",
      "cornerRadius": 0,
      "curveFrom": "{0, 0}",
      "curveMode": 1,
      "curveTo": "{0, 0}",
      "hasCurveFrom": false,
      "hasCurveTo": false,
      "point": "{0, 0}"
    },
    {
      "_class": "curvePoint",
      "cornerRadius": 0,
      "curveFrom": "{0, 1}",
      "curveMode": 1,
      "curveTo": "{0, 1}",
      "hasCurveFrom": false,
      "hasCurveTo": false,
      "point": "{0, 1}"
    },
    {
      "_class": "curvePoint",
      "cornerRadius": 0,
      "curveFrom": "{0.25208181744684366, 1}",
      "curveMode": 1,
      "curveTo": "{0.25208181744684366, 1}",
      "hasCurveFrom": false,
      "hasCurveTo": false,
      "point": "{0.25208181744684366, 1}"
    },
    {
      "_class": "curvePoint",
      "cornerRadius": 0,
      "curveFrom": "{0.25208181744684366, 0.58632676709154119}",
      "curveMode": 1,
      "curveTo": "{0.25208181744684366, 0.58632676709154119}",
      "hasCurveFrom": false,
      "hasCurveTo": false,
      "point": "{0.25208181744684366, 0.58632676709154119}"
    },
    {
      "_class": "curvePoint",
      "cornerRadius": 0,
      "curveFrom": "{0.7495351281429381, 0.58632676709154119}",
      "curveMode": 1,
      "curveTo": "{0.7495351281429381, 0.58632676709154119}",
      "hasCurveFrom": false,
      "hasCurveTo": false,
      "point": "{0.7495351281429381, 0.58632676709154119}"
    },
    {
      "_class": "curvePoint",
      "cornerRadius": 0,
      "curveFrom": "{0.7495351281429381, 1}",
      "curveMode": 1,
      "curveTo": "{0.7495351281429381, 1}",
      "hasCurveFrom": false,
      "hasCurveTo": false,
      "point": "{0.7495351281429381, 1}"
    },
    {
      "_class": "curvePoint",
      "cornerRadius": 0,
      "curveFrom": "{1, 1}",
      "curveMode": 1,
      "curveTo": "{1, 1}",
      "hasCurveFrom": false,
      "hasCurveTo": false,
      "point": "{1, 1}"
    },
    {
      "_class": "curvePoint",
      "cornerRadius": 0,
      "curveFrom": "{1, 0}",
      "curveMode": 1,
      "curveTo": "{1, 0}",
      "hasCurveFrom": false,
      "hasCurveTo": false,
      "point": "{1, 0}"
    },
    {
      "_class": "curvePoint",
      "cornerRadius": 0,
      "curveFrom": "{0.80685584930067134, 0}",
      "curveMode": 4,
      "curveTo": "{0.87751637157409645, 0}",
      "hasCurveFrom": true,
      "hasCurveTo": false,
      "point": "{0.87751637157409645, 0}"
    },
    {
      "_class": "curvePoint",
      "cornerRadius": 0,
      "curveFrom": "{0.7495351281429381, 0.10789993865448853}",
      "curveMode": 4,
      "curveTo": "{0.7495351281429381, 0.048326630768182326}",
      "hasCurveFrom": false,
      "hasCurveTo": true,
      "point": "{0.7495351281429381, 0.10789993865448853}"
    },
    {
      "_class": "curvePoint",
      "cornerRadius": 0,
      "curveFrom": "{0.7495351281429381, 0.39227046554427103}",
      "curveMode": 1,
      "curveTo": "{0.7495351281429381, 0.39227046554427103}",
      "hasCurveFrom": false,
      "hasCurveTo": false,
      "point": "{0.7495351281429381, 0.39227046554427103}"
    },
    {
      "_class": "curvePoint",
      "cornerRadius": 0,
      "curveFrom": "{0.25208181744684366, 0.39227046554427103}",
      "curveMode": 1,
      "curveTo": "{0.25208181744684366, 0.39227046554427103}",
      "hasCurveFrom": false,
      "hasCurveTo": false,
      "point": "{0.25208181744684366, 0.39227046554427103}"
    }
  ],
  "resizingConstraint": 63,
  "resizingType": 0,
  "rotation": 0,
  "shouldBreakMaskChain": false,
  "style": {
    "_class": "style",
    "endMarkerType": 0,
    "miterLimit": 10,
    "startMarkerType": 0,
    "windingRule": 1
  }
}