{
  "_class": "text",
  "attributedString": {
    "_class": "attributedString",
    "attributes": [
      {
        "_class": "stringAttribute",
        "attributes": {
          "MSAttributedStringColorAttribute": {
            "_class": "color",
            "alpha": 1,
            "blue": 0.2901960784313726,
            "green": 0.2901960784313726,
            "red": 0.2901960784313726
          },
          "MSAttributedStringFontAttribute": {
            "_class": "fontDescriptor",
            "attributes": {
              "name": "Arial-BoldMT",
              "size": 14
            }
          },
          "kerning": 0,
          "paragraphStyle": {
            "_class": "paragraphStyle",
            "alignment": 2,
            "allowsDefaultTighteningForTruncation": 0,
            "maximumLineHeight": 17,
            "minimumLineHeight": 17,
            "tighteningFactorForTruncation": 0.05
          },
          "textStyleVerticalAlignmentKey": 0
        },
        "length": 14,
        "location": 0
      }
    ],
    "string": "Corresponsales"
  },
  "automaticallyDrawOnUnderlyingPath": false,
  "booleanOperation": -1,
  "clippingMaskMode": 0,
  "do_objectID": "215F2F0E-0119-446E-AC28-D75E66422D1D",
  "dontSynchroniseWithSymbol": false,
  "exportOptions": {
    "_class": "exportOptions",
    "do_objectID": "98E68ED4-7ED1-4D85-9A00-92C854F053B8",
    "exportFormats": [
    ],
    "includedLayerIds": [
    ],
    "layerOptions": 0,
    "shouldTrim": false
  },
  "frame": {
    "_class": "rect",
    "constrainProportions": false,
    "do_objectID": "D4A91DAA-5CA3-4E61-B63D-F3F42E9EA59D",
    "height": 17,
    "width": 106,
    "x": 12,
    "y": 82
  },
  "glyphBounds": "{{0, 3}, {106, 14}}",
  "hasClippingMask": false,
  "isFixedToViewport": false,
  "isFlippedHorizontal": false,
  "isFlippedVertical": false,
  "isLocked": false,
  "isVisible": true,
  "layerListExpandedType": 0,
  "lineSpacingBehaviour": 2,
  "name": "Corresponsales",
  "nameIsFixed": false,
  "resizingConstraint": 47,
  "resizingType": 0,
  "rotation": 0,
  "shouldBreakMaskChain": false,
  "style": {
    "_class": "style",
    "do_objectID": "7D509711-2EE9-44A3-8FB6-F260AAE4BBCB",
    "endMarkerType": 0,
    "miterLimit": 10,
    "startMarkerType": 0,
    "textStyle": {
      "_class": "textStyle",
      "do_objectID": "F85608A0-4DA9-4C04-97B2-EF2006639434",
      "encodedAttributes": {
        "MSAttributedStringColorAttribute": {
          "_class": "color",
          "alpha": 1,
          "blue": 0.2901960784313726,
          "green": 0.2901960784313726,
          "red": 0.2901960784313726
        },
        "MSAttributedStringFontAttribute": {
          "_class": "fontDescriptor",
          "attributes": {
            "name": "Arial-BoldMT",
            "size": 14
          }
        },
        "kerning": 0,
        "paragraphStyle": {
          "_class": "paragraphStyle",
          "alignment": 2,
          "allowsDefaultTighteningForTruncation": 0,
          "maximumLineHeight": 17,
          "minimumLineHeight": 17,
          "tighteningFactorForTruncation": 0.05
        },
        "textStyleVerticalAlignmentKey": 0
      },
      "verticalAlignment": 0
    },
    "windingRule": 1
  },
  "textBehaviour": 0
}