{
  "_class": "group",
  "booleanOperation": -1,
  "clippingMaskMode": 0,
  "do_objectID": "F9E6BD00-E310-4AC0-A8E5-262CF1BC6F57",
  "exportOptions": {
    "_class": "exportOptions",
    "do_objectID": "8C404D51-C160-4BED-80EA-44160498AB18",
    "exportFormats": [
    ],
    "includedLayerIds": [
    ],
    "layerOptions": 0,
    "shouldTrim": false
  },
  "frame": {
    "_class": "rect",
    "constrainProportions": false,
    "do_objectID": "A14CC1C0-3671-4678-B63C-C7F8C824D308",
    "height": 357,
    "width": 520,
    "x": 103,
    "y": 457
  },
  "groupLayout": {
    "_class": "MSImmutableFreeformGroupLayout",
    "do_objectID": "437C275E-8623-4E56-8285-4CA710783699"
  },
  "hasClickThrough": false,
  "hasClippingMask": false,
  "isFixedToViewport": false,
  "isFlippedHorizontal": false,
  "isFlippedVertical": false,
  "isLocked": false,
  "isVisible": true,
  "layerListExpandedType": 0,
  "layers": [
    {
      "class": "text",
      "id": "879D8427-184B-4318-8FE0-0D2AFB01E48F"
    },
    {
      "class": "text",
      "id": "F64BC242-49E8-48C6-B81F-F5F46289807D"
    },
    {
      "class": "group",
      "id": "BD1B8D54-F0D7-445C-BB11-728465D6FB06"
    }
  ],
  "name": "Group 11",
  "nameIsFixed": false,
  "resizingConstraint": 63,
  "resizingType": 0,
  "rotation": 0,
  "shouldBreakMaskChain": false,
  "style": {
    "_class": "style",
    "do_objectID": "E119223D-B758-4D8E-BE46-353F1D66AD90",
    "endMarkerType": 0,
    "miterLimit": 10,
    "startMarkerType": 0,
    "windingRule": 1
  }
}